poetry_crawling/__init__.py
poetry_crawling-0.1.0.dist-info/WHEEL
poetry_crawling-0.1.0.dist-info/METADATA
poetry_crawling-0.1.0.dist-info/RECORD
